{
  "type": "FeatureCollection",
  "name": "NSW Ports Locations",
  "crs": {
    "type": "name",
    "properties": { "name": "urn:ogc:def:crs:OGC:1.3:CRS84" }
  },
  "features": [
    {
      "type": "Feature",
      "properties": {
        "NAME": "Port Botany"
      },
      "geometry": {
        "type": "Point",
        "coordinates": [151.215439, -33.972157]
      }
    }
  ]
}
