{
  "type": "FeatureCollection",
  "name": "PB_GATENO",
  "crs": {
    "type": "name",
    "properties": { "name": "urn:ogc:def:crs:OGC:1.3:CRS84" }
  },
  "features": [
    {
      "type": "Feature",
      "properties": { "GATE_NUM": "B49a" },
      "geometry": {
        "type": "Point",
        "coordinates": [151.210915985337465, -33.979979092167973]
      }
    }
  ]
}
