{
  "type": "FeatureCollection",
  "name": "PB_GATENO",
  "crs": {
    "type": "name",
    "properties": { "name": "urn:ogc:def:crs:OGC:1.3:CRS84" }
  },
  "features": [
    {
      "type": "Feature",
      "properties": { "GATE_NUM": "B52" },
      "geometry": {
        "type": "Point",
        "coordinates": [151.214465575001356, -33.980092376944476]
      }
    }
  ]
}
