{
  "type": "FeatureCollection",
  "name": "Pork Kembla Inner Harbour",
  "crs": { "type": "name", "properties": { "name": "urn:ogc:def:crs:OGC:1.3:CRS84" } },
  "features": [
    {
      "type": "Feature",
      "properties": { "fid": 1, "Asset name": "Inner Harbour" },
      "geometry": { "type": "Point", "coordinates": [150.89268, -34.45825] }
    }
  ]
}
